repren/__init__.py
repren/claude_skill.py
repren/markdown_renderer.py
repren/py.typed
repren/repren.py
repren/skills/SKILL.md
repren-2.0.0.dist-info/METADATA
repren-2.0.0.dist-info/WHEEL
repren-2.0.0.dist-info/entry_points.txt
repren-2.0.0.dist-info/licenses/LICENSE
repren-2.0.0.dist-info/RECORD
